{
  "type": "File",
  "start": 0,
  "end": 258,
  "loc": {
    "start": {
      "line": 1,
      "column": 0
    },
    "end": {
      "line": 7,
      "column": 0
    }
  },
  "program": {
    "type": "Program",
    "start": 0,
    "end": 258,
    "loc": {
      "start": {
        "line": 1,
        "column": 0
      },
      "end": {
        "line": 7,
        "column": 0
      }
    },
    "sourceType": "module",
    "body": [
      {
        "type": "ImportDeclaration",
        "start": 0,
        "end": 33,
        "loc": {
          "start": {
            "line": 1,
            "column": 0
          },
          "end": {
            "line": 1,
            "column": 33
          }
        },
        "specifiers": [
          {
            "type": "ImportSpecifier",
            "start": 9,
            "end": 15,
            "loc": {
              "start": {
                "line": 1,
                "column": 9
              },
              "end": {
                "line": 1,
                "column": 15
              }
            },
            "imported": {
              "type": "Identifier",
              "start": 9,
              "end": 15,
              "loc": {
                "start": {
                  "line": 1,
                  "column": 9
                },
                "end": {
                  "line": 1,
                  "column": 15
                },
                "identifierName": "Router"
              },
              "name": "Router"
            },
            "local": {
              "type": "Identifier",
              "start": 9,
              "end": 15,
              "loc": {
                "start": {
                  "line": 1,
                  "column": 9
                },
                "end": {
                  "line": 1,
                  "column": 15
                },
                "identifierName": "Router"
              },
              "name": "Router"
            }
          }
        ],
        "source": {
          "type": "StringLiteral",
          "start": 23,
          "end": 32,
          "loc": {
            "start": {
              "line": 1,
              "column": 23
            },
            "end": {
              "line": 1,
              "column": 32
            }
          },
          "extra": {
            "rawValue": "express",
            "raw": "'express'"
          },
          "value": "express"
        }
      },
      {
        "type": "ImportDeclaration",
        "start": 34,
        "end": 84,
        "loc": {
          "start": {
            "line": 2,
            "column": 0
          },
          "end": {
            "line": 2,
            "column": 50
          }
        },
        "specifiers": [
          {
            "type": "ImportDefaultSpecifier",
            "start": 41,
            "end": 51,
            "loc": {
              "start": {
                "line": 2,
                "column": 7
              },
              "end": {
                "line": 2,
                "column": 17
              }
            },
            "local": {
              "type": "Identifier",
              "start": 41,
              "end": 51,
              "loc": {
                "start": {
                  "line": 2,
                  "column": 7
                },
                "end": {
                  "line": 2,
                  "column": 17
                },
                "identifierName": "createUser"
              },
              "name": "createUser"
            }
          }
        ],
        "source": {
          "type": "StringLiteral",
          "start": 57,
          "end": 83,
          "loc": {
            "start": {
              "line": 2,
              "column": 23
            },
            "end": {
              "line": 2,
              "column": 49
            }
          },
          "extra": {
            "rawValue": "./controllers/createUser",
            "raw": "'./controllers/createUser'"
          },
          "value": "./controllers/createUser"
        }
      },
      {
        "type": "Identifier",
        "start": 85,
        "end": 109,
        "loc": {
          "start": {
            "line": 3,
            "column": 0
          },
          "end": {
            "line": 3,
            "column": 24
          }
        },
        "declarations": [
          {
            "type": "VariableDeclarator",
            "start": 91,
            "end": 108,
            "loc": {
              "start": {
                "line": 3,
                "column": 6
              },
              "end": {
                "line": 3,
                "column": 23
              }
            },
            "id": {
              "type": "Identifier",
              "start": 91,
              "end": 97,
              "loc": {
                "start": {
                  "line": 3,
                  "column": 6
                },
                "end": {
                  "line": 3,
                  "column": 12
                },
                "identifierName": "routes"
              },
              "name": "routes"
            },
            "init": {
              "type": "CallExpression",
              "start": 100,
              "end": 108,
              "loc": {
                "start": {
                  "line": 3,
                  "column": 15
                },
                "end": {
                  "line": 3,
                  "column": 23
                }
              },
              "callee": {
                "type": "Identifier",
                "start": 100,
                "end": 106,
                "loc": {
                  "start": {
                    "line": 3,
                    "column": 15
                  },
                  "end": {
                    "line": 3,
                    "column": 21
                  },
                  "identifierName": "Router"
                },
                "name": "Router"
              },
              "arguments": []
            }
          }
        ],
        "kind": "const",
        "name": "_",
        "leadingComments": [],
        "trailingComments": []
      },
      {
        "type": "ExpressionStatement",
        "start": 110,
        "end": 193,
        "loc": {
          "start": {
            "line": 4,
            "column": 0
          },
          "end": {
            "line": 4,
            "column": 83
          }
        },
        "expression": {
          "type": "CallExpression",
          "start": 110,
          "end": 192,
          "loc": {
            "start": {
              "line": 4,
              "column": 0
            },
            "end": {
              "line": 4,
              "column": 82
            }
          },
          "callee": {
            "type": "MemberExpression",
            "start": 110,
            "end": 120,
            "loc": {
              "start": {
                "line": 4,
                "column": 0
              },
              "end": {
                "line": 4,
                "column": 10
              }
            },
            "object": {
              "type": "Identifier",
              "start": 110,
              "end": 116,
              "loc": {
                "start": {
                  "line": 4,
                  "column": 0
                },
                "end": {
                  "line": 4,
                  "column": 6
                },
                "identifierName": "routes"
              },
              "name": "routes"
            },
            "property": {
              "type": "Identifier",
              "start": 117,
              "end": 120,
              "loc": {
                "start": {
                  "line": 4,
                  "column": 7
                },
                "end": {
                  "line": 4,
                  "column": 10
                },
                "identifierName": "get"
              },
              "name": "get"
            },
            "computed": false
          },
          "arguments": [
            {
              "type": "StringLiteral",
              "start": 121,
              "end": 124,
              "loc": {
                "start": {
                  "line": 4,
                  "column": 11
                },
                "end": {
                  "line": 4,
                  "column": 14
                }
              },
              "extra": {
                "rawValue": "/",
                "raw": "'/'"
              },
              "value": "/"
            },
            {
              "type": "ArrowFunctionExpression",
              "start": 126,
              "end": 191,
              "loc": {
                "start": {
                  "line": 4,
                  "column": 16
                },
                "end": {
                  "line": 4,
                  "column": 81
                }
              },
              "id": null,
              "generator": false,
              "expression": true,
              "async": false,
              "params": [
                {
                  "type": "Identifier",
                  "start": 127,
                  "end": 134,
                  "loc": {
                    "start": {
                      "line": 4,
                      "column": 17
                    },
                    "end": {
                      "line": 4,
                      "column": 24
                    },
                    "identifierName": "request"
                  },
                  "name": "request"
                },
                {
                  "type": "Identifier",
                  "start": 136,
                  "end": 144,
                  "loc": {
                    "start": {
                      "line": 4,
                      "column": 26
                    },
                    "end": {
                      "line": 4,
                      "column": 34
                    },
                    "identifierName": "response"
                  },
                  "name": "response"
                }
              ],
              "body": {
                "type": "CallExpression",
                "start": 149,
                "end": 191,
                "loc": {
                  "start": {
                    "line": 4,
                    "column": 39
                  },
                  "end": {
                    "line": 4,
                    "column": 81
                  }
                },
                "callee": {
                  "type": "MemberExpression",
                  "start": 149,
                  "end": 162,
                  "loc": {
                    "start": {
                      "line": 4,
                      "column": 39
                    },
                    "end": {
                      "line": 4,
                      "column": 52
                    }
                  },
                  "object": {
                    "type": "Identifier",
                    "start": 149,
                    "end": 157,
                    "loc": {
                      "start": {
                        "line": 4,
                        "column": 39
                      },
                      "end": {
                        "line": 4,
                        "column": 47
                      },
                      "identifierName": "response"
                    },
                    "name": "response"
                  },
                  "property": {
                    "type": "Identifier",
                    "start": 158,
                    "end": 162,
                    "loc": {
                      "start": {
                        "line": 4,
                        "column": 48
                      },
                      "end": {
                        "line": 4,
                        "column": 52
                      },
                      "identifierName": "send"
                    },
                    "name": "send"
                  },
                  "computed": false
                },
                "arguments": [
                  {
                    "type": "StringLiteral",
                    "start": 163,
                    "end": 190,
                    "loc": {
                      "start": {
                        "line": 4,
                        "column": 53
                      },
                      "end": {
                        "line": 4,
                        "column": 80
                      }
                    },
                    "extra": {
                      "rawValue": "CJ Andrade Management API",
                      "raw": "'CJ Andrade Management API'"
                    },
                    "value": "CJ Andrade Management API"
                  }
                ]
              }
            }
          ]
        }
      },
      {
        "type": "ExpressionStatement",
        "start": 194,
        "end": 234,
        "loc": {
          "start": {
            "line": 5,
            "column": 0
          },
          "end": {
            "line": 5,
            "column": 40
          }
        },
        "expression": {
          "type": "CallExpression",
          "start": 194,
          "end": 233,
          "loc": {
            "start": {
              "line": 5,
              "column": 0
            },
            "end": {
              "line": 5,
              "column": 39
            }
          },
          "callee": {
            "type": "MemberExpression",
            "start": 194,
            "end": 205,
            "loc": {
              "start": {
                "line": 5,
                "column": 0
              },
              "end": {
                "line": 5,
                "column": 11
              }
            },
            "object": {
              "type": "Identifier",
              "start": 194,
              "end": 200,
              "loc": {
                "start": {
                  "line": 5,
                  "column": 0
                },
                "end": {
                  "line": 5,
                  "column": 6
                },
                "identifierName": "routes"
              },
              "name": "routes"
            },
            "property": {
              "type": "Identifier",
              "start": 201,
              "end": 205,
              "loc": {
                "start": {
                  "line": 5,
                  "column": 7
                },
                "end": {
                  "line": 5,
                  "column": 11
                },
                "identifierName": "post"
              },
              "name": "post"
            },
            "computed": false
          },
          "arguments": [
            {
              "type": "StringLiteral",
              "start": 206,
              "end": 220,
              "loc": {
                "start": {
                  "line": 5,
                  "column": 12
                },
                "end": {
                  "line": 5,
                  "column": 26
                }
              },
              "extra": {
                "rawValue": "/create-user",
                "raw": "'/create-user'"
              },
              "value": "/create-user"
            },
            {
              "type": "Identifier",
              "start": 222,
              "end": 232,
              "loc": {
                "start": {
                  "line": 5,
                  "column": 28
                },
                "end": {
                  "line": 5,
                  "column": 38
                },
                "identifierName": "createUser"
              },
              "name": "createUser"
            }
          ]
        }
      },
      {
        "type": "Identifier",
        "start": 235,
        "end": 257,
        "loc": {
          "start": {
            "line": 6,
            "column": 0
          },
          "end": {
            "line": 6,
            "column": 22
          }
        },
        "declaration": {
          "type": "Identifier",
          "start": 250,
          "end": 256,
          "loc": {
            "start": {
              "line": 6,
              "column": 15
            },
            "end": {
              "line": 6,
              "column": 21
            },
            "identifierName": "routes"
          },
          "name": "routes"
        },
        "name": "_",
        "leadingComments": [],
        "trailingComments": []
      },
      {
        "type": "ExportDefaultDeclaration",
        "start": 235,
        "end": 257,
        "loc": {
          "start": {
            "line": 6,
            "column": 0
          },
          "end": {
            "line": 6,
            "column": 22
          }
        },
        "declaration": {
          "type": "VariableDeclaration",
          "start": 85,
          "end": 109,
          "loc": {
            "start": {
              "line": 3,
              "column": 0
            },
            "end": {
              "line": 3,
              "column": 24
            }
          },
          "declarations": [
            {
              "type": "VariableDeclarator",
              "start": 91,
              "end": 108,
              "loc": {
                "start": {
                  "line": 3,
                  "column": 6
                },
                "end": {
                  "line": 3,
                  "column": 23
                }
              },
              "id": {
                "type": "Identifier",
                "start": 91,
                "end": 97,
                "loc": {
                  "start": {
                    "line": 3,
                    "column": 6
                  },
                  "end": {
                    "line": 3,
                    "column": 12
                  },
                  "identifierName": "routes"
                },
                "name": "routes"
              },
              "init": {
                "type": "CallExpression",
                "start": 100,
                "end": 108,
                "loc": {
                  "start": {
                    "line": 3,
                    "column": 15
                  },
                  "end": {
                    "line": 3,
                    "column": 23
                  }
                },
                "callee": {
                  "type": "Identifier",
                  "start": 100,
                  "end": 106,
                  "loc": {
                    "start": {
                      "line": 3,
                      "column": 15
                    },
                    "end": {
                      "line": 3,
                      "column": 21
                    },
                    "identifierName": "Router"
                  },
                  "name": "Router"
                },
                "arguments": []
              }
            }
          ],
          "kind": "const",
          "leadingComments": [],
          "trailingComments": []
        }
      }
    ],
    "directives": []
  },
  "comments": [],
  "tokens": [
    {
      "type": {
        "label": "import",
        "keyword": "import",
        "beforeExpr": false,
        "startsExpr": true,
        "rightAssociative": false,
        "isLoop": false,
        "isAssign": false,
        "prefix": false,
        "postfix": false,
        "binop": null,
        "updateContext": null
      },
      "value": "import",
      "start": 0,
      "end": 6,
      "loc": {
        "start": {
          "line": 1,
          "column": 0
        },
        "end": {
          "line": 1,
          "column": 6
        }
      }
    },
    {
      "type": {
        "label": "{",
        "beforeExpr": true,
        "startsExpr": true,
        "rightAssociative": false,
        "isLoop": false,
        "isAssign": false,
        "prefix": false,
        "postfix": false,
        "binop": null
      },
      "start": 7,
      "end": 8,
      "loc": {
        "start": {
          "line": 1,
          "column": 7
        },
        "end": {
          "line": 1,
          "column": 8
        }
      }
    },
    {
      "type": {
        "label": "name",
        "beforeExpr": false,
        "startsExpr": true,
        "rightAssociative": false,
        "isLoop": false,
        "isAssign": false,
        "prefix": false,
        "postfix": false,
        "binop": null
      },
      "value": "Router",
      "start": 9,
      "end": 15,
      "loc": {
        "start": {
          "line": 1,
          "column": 9
        },
        "end": {
          "line": 1,
          "column": 15
        }
      }
    },
    {
      "type": {
        "label": "}",
        "beforeExpr": false,
        "startsExpr": false,
        "rightAssociative": false,
        "isLoop": false,
        "isAssign": false,
        "prefix": false,
        "postfix": false,
        "binop": null
      },
      "start": 16,
      "end": 17,
      "loc": {
        "start": {
          "line": 1,
          "column": 16
        },
        "end": {
          "line": 1,
          "column": 17
        }
      }
    },
    {
      "type": {
        "label": "name",
        "beforeExpr": false,
        "startsExpr": true,
        "rightAssociative": false,
        "isLoop": false,
        "isAssign": false,
        "prefix": false,
        "postfix": false,
        "binop": null
      },
      "value": "from",
      "start": 18,
      "end": 22,
      "loc": {
        "start": {
          "line": 1,
          "column": 18
        },
        "end": {
          "line": 1,
          "column": 22
        }
      }
    },
    {
      "type": {
        "label": "string",
        "beforeExpr": false,
        "startsExpr": true,
        "rightAssociative": false,
        "isLoop": false,
        "isAssign": false,
        "prefix": false,
        "postfix": false,
        "binop": null,
        "updateContext": null
      },
      "value": "express",
      "start": 23,
      "end": 32,
      "loc": {
        "start": {
          "line": 1,
          "column": 23
        },
        "end": {
          "line": 1,
          "column": 32
        }
      }
    },
    {
      "type": {
        "label": ";",
        "beforeExpr": true,
        "startsExpr": false,
        "rightAssociative": false,
        "isLoop": false,
        "isAssign": false,
        "prefix": false,
        "postfix": false,
        "binop": null,
        "updateContext": null
      },
      "start": 32,
      "end": 33,
      "loc": {
        "start": {
          "line": 1,
          "column": 32
        },
        "end": {
          "line": 1,
          "column": 33
        }
      }
    },
    {
      "type": {
        "label": "import",
        "keyword": "import",
        "beforeExpr": false,
        "startsExpr": true,
        "rightAssociative": false,
        "isLoop": false,
        "isAssign": false,
        "prefix": false,
        "postfix": false,
        "binop": null,
        "updateContext": null
      },
      "value": "import",
      "start": 34,
      "end": 40,
      "loc": {
        "start": {
          "line": 2,
          "column": 0
        },
        "end": {
          "line": 2,
          "column": 6
        }
      }
    },
    {
      "type": {
        "label": "name",
        "beforeExpr": false,
        "startsExpr": true,
        "rightAssociative": false,
        "isLoop": false,
        "isAssign": false,
        "prefix": false,
        "postfix": false,
        "binop": null
      },
      "value": "createUser",
      "start": 41,
      "end": 51,
      "loc": {
        "start": {
          "line": 2,
          "column": 7
        },
        "end": {
          "line": 2,
          "column": 17
        }
      }
    },
    {
      "type": {
        "label": "name",
        "beforeExpr": false,
        "startsExpr": true,
        "rightAssociative": false,
        "isLoop": false,
        "isAssign": false,
        "prefix": false,
        "postfix": false,
        "binop": null
      },
      "value": "from",
      "start": 52,
      "end": 56,
      "loc": {
        "start": {
          "line": 2,
          "column": 18
        },
        "end": {
          "line": 2,
          "column": 22
        }
      }
    },
    {
      "type": {
        "label": "string",
        "beforeExpr": false,
        "startsExpr": true,
        "rightAssociative": false,
        "isLoop": false,
        "isAssign": false,
        "prefix": false,
        "postfix": false,
        "binop": null,
        "updateContext": null
      },
      "value": "./controllers/createUser",
      "start": 57,
      "end": 83,
      "loc": {
        "start": {
          "line": 2,
          "column": 23
        },
        "end": {
          "line": 2,
          "column": 49
        }
      }
    },
    {
      "type": {
        "label": ";",
        "beforeExpr": true,
        "startsExpr": false,
        "rightAssociative": false,
        "isLoop": false,
        "isAssign": false,
        "prefix": false,
        "postfix": false,
        "binop": null,
        "updateContext": null
      },
      "start": 83,
      "end": 84,
      "loc": {
        "start": {
          "line": 2,
          "column": 49
        },
        "end": {
          "line": 2,
          "column": 50
        }
      }
    },
    {
      "type": {
        "label": "const",
        "keyword": "const",
        "beforeExpr": false,
        "startsExpr": false,
        "rightAssociative": false,
        "isLoop": false,
        "isAssign": false,
        "prefix": false,
        "postfix": false,
        "binop": null,
        "updateContext": null
      },
      "value": "const",
      "start": 85,
      "end": 90,
      "loc": {
        "start": {
          "line": 3,
          "column": 0
        },
        "end": {
          "line": 3,
          "column": 5
        }
      }
    },
    {
      "type": {
        "label": "name",
        "beforeExpr": false,
        "startsExpr": true,
        "rightAssociative": false,
        "isLoop": false,
        "isAssign": false,
        "prefix": false,
        "postfix": false,
        "binop": null
      },
      "value": "routes",
      "start": 91,
      "end": 97,
      "loc": {
        "start": {
          "line": 3,
          "column": 6
        },
        "end": {
          "line": 3,
          "column": 12
        }
      }
    },
    {
      "type": {
        "label": "=",
        "beforeExpr": true,
        "startsExpr": false,
        "rightAssociative": false,
        "isLoop": false,
        "isAssign": true,
        "prefix": false,
        "postfix": false,
        "binop": null,
        "updateContext": null
      },
      "value": "=",
      "start": 98,
      "end": 99,
      "loc": {
        "start": {
          "line": 3,
          "column": 13
        },
        "end": {
          "line": 3,
          "column": 14
        }
      }
    },
    {
      "type": {
        "label": "name",
        "beforeExpr": false,
        "startsExpr": true,
        "rightAssociative": false,
        "isLoop": false,
        "isAssign": false,
        "prefix": false,
        "postfix": false,
        "binop": null
      },
      "value": "Router",
      "start": 100,
      "end": 106,
      "loc": {
        "start": {
          "line": 3,
          "column": 15
        },
        "end": {
          "line": 3,
          "column": 21
        }
      }
    },
    {
      "type": {
        "label": "(",
        "beforeExpr": true,
        "startsExpr": true,
        "rightAssociative": false,
        "isLoop": false,
        "isAssign": false,
        "prefix": false,
        "postfix": false,
        "binop": null
      },
      "start": 106,
      "end": 107,
      "loc": {
        "start": {
          "line": 3,
          "column": 21
        },
        "end": {
          "line": 3,
          "column": 22
        }
      }
    },
    {
      "type": {
        "label": ")",
        "beforeExpr": false,
        "startsExpr": false,
        "rightAssociative": false,
        "isLoop": false,
        "isAssign": false,
        "prefix": false,
        "postfix": false,
        "binop": null
      },
      "start": 107,
      "end": 108,
      "loc": {
        "start": {
          "line": 3,
          "column": 22
        },
        "end": {
          "line": 3,
          "column": 23
        }
      }
    },
    {
      "type": {
        "label": ";",
        "beforeExpr": true,
        "startsExpr": false,
        "rightAssociative": false,
        "isLoop": false,
        "isAssign": false,
        "prefix": false,
        "postfix": false,
        "binop": null,
        "updateContext": null
      },
      "start": 108,
      "end": 109,
      "loc": {
        "start": {
          "line": 3,
          "column": 23
        },
        "end": {
          "line": 3,
          "column": 24
        }
      }
    },
    {
      "type": {
        "label": "name",
        "beforeExpr": false,
        "startsExpr": true,
        "rightAssociative": false,
        "isLoop": false,
        "isAssign": false,
        "prefix": false,
        "postfix": false,
        "binop": null
      },
      "value": "routes",
      "start": 110,
      "end": 116,
      "loc": {
        "start": {
          "line": 4,
          "column": 0
        },
        "end": {
          "line": 4,
          "column": 6
        }
      }
    },
    {
      "type": {
        "label": ".",
        "beforeExpr": false,
        "startsExpr": false,
        "rightAssociative": false,
        "isLoop": false,
        "isAssign": false,
        "prefix": false,
        "postfix": false,
        "binop": null,
        "updateContext": null
      },
      "start": 116,
      "end": 117,
      "loc": {
        "start": {
          "line": 4,
          "column": 6
        },
        "end": {
          "line": 4,
          "column": 7
        }
      }
    },
    {
      "type": {
        "label": "name",
        "beforeExpr": false,
        "startsExpr": true,
        "rightAssociative": false,
        "isLoop": false,
        "isAssign": false,
        "prefix": false,
        "postfix": false,
        "binop": null
      },
      "value": "get",
      "start": 117,
      "end": 120,
      "loc": {
        "start": {
          "line": 4,
          "column": 7
        },
        "end": {
          "line": 4,
          "column": 10
        }
      }
    },
    {
      "type": {
        "label": "(",
        "beforeExpr": true,
        "startsExpr": true,
        "rightAssociative": false,
        "isLoop": false,
        "isAssign": false,
        "prefix": false,
        "postfix": false,
        "binop": null
      },
      "start": 120,
      "end": 121,
      "loc": {
        "start": {
          "line": 4,
          "column": 10
        },
        "end": {
          "line": 4,
          "column": 11
        }
      }
    },
    {
      "type": {
        "label": "string",
        "beforeExpr": false,
        "startsExpr": true,
        "rightAssociative": false,
        "isLoop": false,
        "isAssign": false,
        "prefix": false,
        "postfix": false,
        "binop": null,
        "updateContext": null
      },
      "value": "/",
      "start": 121,
      "end": 124,
      "loc": {
        "start": {
          "line": 4,
          "column": 11
        },
        "end": {
          "line": 4,
          "column": 14
        }
      }
    },
    {
      "type": {
        "label": ",",
        "beforeExpr": true,
        "startsExpr": false,
        "rightAssociative": false,
        "isLoop": false,
        "isAssign": false,
        "prefix": false,
        "postfix": false,
        "binop": null,
        "updateContext": null
      },
      "start": 124,
      "end": 125,
      "loc": {
        "start": {
          "line": 4,
          "column": 14
        },
        "end": {
          "line": 4,
          "column": 15
        }
      }
    },
    {
      "type": {
        "label": "(",
        "beforeExpr": true,
        "startsExpr": true,
        "rightAssociative": false,
        "isLoop": false,
        "isAssign": false,
        "prefix": false,
        "postfix": false,
        "binop": null
      },
      "start": 126,
      "end": 127,
      "loc": {
        "start": {
          "line": 4,
          "column": 16
        },
        "end": {
          "line": 4,
          "column": 17
        }
      }
    },
    {
      "type": {
        "label": "name",
        "beforeExpr": false,
        "startsExpr": true,
        "rightAssociative": false,
        "isLoop": false,
        "isAssign": false,
        "prefix": false,
        "postfix": false,
        "binop": null
      },
      "value": "request",
      "start": 127,
      "end": 134,
      "loc": {
        "start": {
          "line": 4,
          "column": 17
        },
        "end": {
          "line": 4,
          "column": 24
        }
      }
    },
    {
      "type": {
        "label": ",",
        "beforeExpr": true,
        "startsExpr": false,
        "rightAssociative": false,
        "isLoop": false,
        "isAssign": false,
        "prefix": false,
        "postfix": false,
        "binop": null,
        "updateContext": null
      },
      "start": 134,
      "end": 135,
      "loc": {
        "start": {
          "line": 4,
          "column": 24
        },
        "end": {
          "line": 4,
          "column": 25
        }
      }
    },
    {
      "type": {
        "label": "name",
        "beforeExpr": false,
        "startsExpr": true,
        "rightAssociative": false,
        "isLoop": false,
        "isAssign": false,
        "prefix": false,
        "postfix": false,
        "binop": null
      },
      "value": "response",
      "start": 136,
      "end": 144,
      "loc": {
        "start": {
          "line": 4,
          "column": 26
        },
        "end": {
          "line": 4,
          "column": 34
        }
      }
    },
    {
      "type": {
        "label": ")",
        "beforeExpr": false,
        "startsExpr": false,
        "rightAssociative": false,
        "isLoop": false,
        "isAssign": false,
        "prefix": false,
        "postfix": false,
        "binop": null
      },
      "start": 144,
      "end": 145,
      "loc": {
        "start": {
          "line": 4,
          "column": 34
        },
        "end": {
          "line": 4,
          "column": 35
        }
      }
    },
    {
      "type": {
        "label": "=>",
        "beforeExpr": true,
        "startsExpr": false,
        "rightAssociative": false,
        "isLoop": false,
        "isAssign": false,
        "prefix": false,
        "postfix": false,
        "binop": null,
        "updateContext": null
      },
      "start": 146,
      "end": 148,
      "loc": {
        "start": {
          "line": 4,
          "column": 36
        },
        "end": {
          "line": 4,
          "column": 38
        }
      }
    },
    {
      "type": {
        "label": "name",
        "beforeExpr": false,
        "startsExpr": true,
        "rightAssociative": false,
        "isLoop": false,
        "isAssign": false,
        "prefix": false,
        "postfix": false,
        "binop": null
      },
      "value": "response",
      "start": 149,
      "end": 157,
      "loc": {
        "start": {
          "line": 4,
          "column": 39
        },
        "end": {
          "line": 4,
          "column": 47
        }
      }
    },
    {
      "type": {
        "label": ".",
        "beforeExpr": false,
        "startsExpr": false,
        "rightAssociative": false,
        "isLoop": false,
        "isAssign": false,
        "prefix": false,
        "postfix": false,
        "binop": null,
        "updateContext": null
      },
      "start": 157,
      "end": 158,
      "loc": {
        "start": {
          "line": 4,
          "column": 47
        },
        "end": {
          "line": 4,
          "column": 48
        }
      }
    },
    {
      "type": {
        "label": "name",
        "beforeExpr": false,
        "startsExpr": true,
        "rightAssociative": false,
        "isLoop": false,
        "isAssign": false,
        "prefix": false,
        "postfix": false,
        "binop": null
      },
      "value": "send",
      "start": 158,
      "end": 162,
      "loc": {
        "start": {
          "line": 4,
          "column": 48
        },
        "end": {
          "line": 4,
          "column": 52
        }
      }
    },
    {
      "type": {
        "label": "(",
        "beforeExpr": true,
        "startsExpr": true,
        "rightAssociative": false,
        "isLoop": false,
        "isAssign": false,
        "prefix": false,
        "postfix": false,
        "binop": null
      },
      "start": 162,
      "end": 163,
      "loc": {
        "start": {
          "line": 4,
          "column": 52
        },
        "end": {
          "line": 4,
          "column": 53
        }
      }
    },
    {
      "type": {
        "label": "string",
        "beforeExpr": false,
        "startsExpr": true,
        "rightAssociative": false,
        "isLoop": false,
        "isAssign": false,
        "prefix": false,
        "postfix": false,
        "binop": null,
        "updateContext": null
      },
      "value": "CJ Andrade Management API",
      "start": 163,
      "end": 190,
      "loc": {
        "start": {
          "line": 4,
          "column": 53
        },
        "end": {
          "line": 4,
          "column": 80
        }
      }
    },
    {
      "type": {
        "label": ")",
        "beforeExpr": false,
        "startsExpr": false,
        "rightAssociative": false,
        "isLoop": false,
        "isAssign": false,
        "prefix": false,
        "postfix": false,
        "binop": null
      },
      "start": 190,
      "end": 191,
      "loc": {
        "start": {
          "line": 4,
          "column": 80
        },
        "end": {
          "line": 4,
          "column": 81
        }
      }
    },
    {
      "type": {
        "label": ")",
        "beforeExpr": false,
        "startsExpr": false,
        "rightAssociative": false,
        "isLoop": false,
        "isAssign": false,
        "prefix": false,
        "postfix": false,
        "binop": null
      },
      "start": 191,
      "end": 192,
      "loc": {
        "start": {
          "line": 4,
          "column": 81
        },
        "end": {
          "line": 4,
          "column": 82
        }
      }
    },
    {
      "type": {
        "label": ";",
        "beforeExpr": true,
        "startsExpr": false,
        "rightAssociative": false,
        "isLoop": false,
        "isAssign": false,
        "prefix": false,
        "postfix": false,
        "binop": null,
        "updateContext": null
      },
      "start": 192,
      "end": 193,
      "loc": {
        "start": {
          "line": 4,
          "column": 82
        },
        "end": {
          "line": 4,
          "column": 83
        }
      }
    },
    {
      "type": {
        "label": "name",
        "beforeExpr": false,
        "startsExpr": true,
        "rightAssociative": false,
        "isLoop": false,
        "isAssign": false,
        "prefix": false,
        "postfix": false,
        "binop": null
      },
      "value": "routes",
      "start": 194,
      "end": 200,
      "loc": {
        "start": {
          "line": 5,
          "column": 0
        },
        "end": {
          "line": 5,
          "column": 6
        }
      }
    },
    {
      "type": {
        "label": ".",
        "beforeExpr": false,
        "startsExpr": false,
        "rightAssociative": false,
        "isLoop": false,
        "isAssign": false,
        "prefix": false,
        "postfix": false,
        "binop": null,
        "updateContext": null
      },
      "start": 200,
      "end": 201,
      "loc": {
        "start": {
          "line": 5,
          "column": 6
        },
        "end": {
          "line": 5,
          "column": 7
        }
      }
    },
    {
      "type": {
        "label": "name",
        "beforeExpr": false,
        "startsExpr": true,
        "rightAssociative": false,
        "isLoop": false,
        "isAssign": false,
        "prefix": false,
        "postfix": false,
        "binop": null
      },
      "value": "post",
      "start": 201,
      "end": 205,
      "loc": {
        "start": {
          "line": 5,
          "column": 7
        },
        "end": {
          "line": 5,
          "column": 11
        }
      }
    },
    {
      "type": {
        "label": "(",
        "beforeExpr": true,
        "startsExpr": true,
        "rightAssociative": false,
        "isLoop": false,
        "isAssign": false,
        "prefix": false,
        "postfix": false,
        "binop": null
      },
      "start": 205,
      "end": 206,
      "loc": {
        "start": {
          "line": 5,
          "column": 11
        },
        "end": {
          "line": 5,
          "column": 12
        }
      }
    },
    {
      "type": {
        "label": "string",
        "beforeExpr": false,
        "startsExpr": true,
        "rightAssociative": false,
        "isLoop": false,
        "isAssign": false,
        "prefix": false,
        "postfix": false,
        "binop": null,
        "updateContext": null
      },
      "value": "/create-user",
      "start": 206,
      "end": 220,
      "loc": {
        "start": {
          "line": 5,
          "column": 12
        },
        "end": {
          "line": 5,
          "column": 26
        }
      }
    },
    {
      "type": {
        "label": ",",
        "beforeExpr": true,
        "startsExpr": false,
        "rightAssociative": false,
        "isLoop": false,
        "isAssign": false,
        "prefix": false,
        "postfix": false,
        "binop": null,
        "updateContext": null
      },
      "start": 220,
      "end": 221,
      "loc": {
        "start": {
          "line": 5,
          "column": 26
        },
        "end": {
          "line": 5,
          "column": 27
        }
      }
    },
    {
      "type": {
        "label": "name",
        "beforeExpr": false,
        "startsExpr": true,
        "rightAssociative": false,
        "isLoop": false,
        "isAssign": false,
        "prefix": false,
        "postfix": false,
        "binop": null
      },
      "value": "createUser",
      "start": 222,
      "end": 232,
      "loc": {
        "start": {
          "line": 5,
          "column": 28
        },
        "end": {
          "line": 5,
          "column": 38
        }
      }
    },
    {
      "type": {
        "label": ")",
        "beforeExpr": false,
        "startsExpr": false,
        "rightAssociative": false,
        "isLoop": false,
        "isAssign": false,
        "prefix": false,
        "postfix": false,
        "binop": null
      },
      "start": 232,
      "end": 233,
      "loc": {
        "start": {
          "line": 5,
          "column": 38
        },
        "end": {
          "line": 5,
          "column": 39
        }
      }
    },
    {
      "type": {
        "label": ";",
        "beforeExpr": true,
        "startsExpr": false,
        "rightAssociative": false,
        "isLoop": false,
        "isAssign": false,
        "prefix": false,
        "postfix": false,
        "binop": null,
        "updateContext": null
      },
      "start": 233,
      "end": 234,
      "loc": {
        "start": {
          "line": 5,
          "column": 39
        },
        "end": {
          "line": 5,
          "column": 40
        }
      }
    },
    {
      "type": {
        "label": "export",
        "keyword": "export",
        "beforeExpr": false,
        "startsExpr": false,
        "rightAssociative": false,
        "isLoop": false,
        "isAssign": false,
        "prefix": false,
        "postfix": false,
        "binop": null,
        "updateContext": null
      },
      "value": "export",
      "start": 235,
      "end": 241,
      "loc": {
        "start": {
          "line": 6,
          "column": 0
        },
        "end": {
          "line": 6,
          "column": 6
        }
      }
    },
    {
      "type": {
        "label": "default",
        "keyword": "default",
        "beforeExpr": true,
        "startsExpr": false,
        "rightAssociative": false,
        "isLoop": false,
        "isAssign": false,
        "prefix": false,
        "postfix": false,
        "binop": null,
        "updateContext": null
      },
      "value": "default",
      "start": 242,
      "end": 249,
      "loc": {
        "start": {
          "line": 6,
          "column": 7
        },
        "end": {
          "line": 6,
          "column": 14
        }
      }
    },
    {
      "type": {
        "label": "name",
        "beforeExpr": false,
        "startsExpr": true,
        "rightAssociative": false,
        "isLoop": false,
        "isAssign": false,
        "prefix": false,
        "postfix": false,
        "binop": null
      },
      "value": "routes",
      "start": 250,
      "end": 256,
      "loc": {
        "start": {
          "line": 6,
          "column": 15
        },
        "end": {
          "line": 6,
          "column": 21
        }
      }
    },
    {
      "type": {
        "label": ";",
        "beforeExpr": true,
        "startsExpr": false,
        "rightAssociative": false,
        "isLoop": false,
        "isAssign": false,
        "prefix": false,
        "postfix": false,
        "binop": null,
        "updateContext": null
      },
      "start": 256,
      "end": 257,
      "loc": {
        "start": {
          "line": 6,
          "column": 21
        },
        "end": {
          "line": 6,
          "column": 22
        }
      }
    },
    {
      "type": {
        "label": "eof",
        "beforeExpr": false,
        "startsExpr": false,
        "rightAssociative": false,
        "isLoop": false,
        "isAssign": false,
        "prefix": false,
        "postfix": false,
        "binop": null,
        "updateContext": null
      },
      "start": 258,
      "end": 258,
      "loc": {
        "start": {
          "line": 7,
          "column": 0
        },
        "end": {
          "line": 7,
          "column": 0
        }
      }
    }
  ]
}